<?xml version="1.0" encoding="UTF-8"?>

<!-- generated on 2024-09-27 16:57:53 by Eclipse SUMO duarouter Version 1.20.0
<configuration xmlns:xsi="http://www.w3.org/2001/XMLSchema-instance" xsi:noNamespaceSchemaLocation="http://sumo.dlr.de/xsd/duarouterConfiguration.xsd">

    <input>
        <net-file value="osm.net.xml"/>
        <route-files value="geo.trips.xml"/>
    </input>

    <output>
        <output-file value="geo.rou.xml"/>
        <write-trips.geo value="true"/>
    </output>

</configuration>
-->

<routes xmlns:xsi="http://www.w3.org/2001/XMLSchema-instance" xsi:noNamespaceSchemaLocation="http://sumo.dlr.de/xsd/routes_file.xsd">
    <vType id="veh_passenger" vClass="passenger"/>
    <vehicle id="veh0" type="veh_passenger" depart="0.00" departLane="best">
        <routeDistribution last="0">
            <route cost="113.82" probability="1.00000000" edges="70200194#1 -70056694#1 -70056694#0 -664980454 77712876#4 539414316 70080980#2 70080980#3 70080980#4 70080980#5 70080980#6 70080979#4 70080979#5 70080979#6 70080979#7 77790788#0 77790788#1 77790788#2 77790788#3 77790788#4 -85631072#4 -85631072#3 -147412866#0"/>
        </routeDistribution>
    </vehicle>
    <vehicle id="veh1" type="veh_passenger" depart="1.82" departLane="best" departSpeed="max">
        <routeDistribution last="0">
            <route cost="84.84" probability="1.00000000" edges="-85701987#4 -85701987#3 -85701987#2 -85701987#1 -85701987#0 -691704911 -1075116935#0 -78684176#3 363237442#0 363237442#1 890032153 76845626#0 76845626#1 -77948714#2"/>
        </routeDistribution>
    </vehicle>
</routes>
